prism/__init__.py
prism/core/__init__.py
prism/core/analyzer.py
prism/core/analyzer_broken.py
prism/core/analyzer_fixed.py
prism/core/models.py
prism/core/person_profiler.py
prism/core/relationship_detector.py
prism/utils/__init__.py
prism/utils/helpers.py
prismintelligence-0.1.0.dist-info/METADATA
prismintelligence-0.1.0.dist-info/WHEEL
prismintelligence-0.1.0.dist-info/top_level.txt
prismintelligence-0.1.0.dist-info/RECORD
