Metadata-Version: 2.4
Name: prismintelligence
Version: 0.1.0
Summary: Revolutionary AI Behavioral Psychology Engine - FBI-Level Human Relationship Analysis
Home-page: https://github.com/Prism-Intelligence/Prism
Author: Olaoluwasubomi Aduloju & Prism Intelligence
Author-email: i@olaoluwasubomi.com
Classifier: Development Status :: 2 - Pre-Alpha
Classifier: Intended Audience :: Developers
Classifier: Topic :: Scientific/Engineering :: Artificial Intelligence
Classifier: Programming Language :: Python :: 3
Requires-Python: >=3.8
Requires-Dist: torch>=1.9.0
Requires-Dist: torchvision>=0.10.0
Requires-Dist: transformers>=4.20.0
Requires-Dist: ultralytics>=8.0.0
Requires-Dist: Pillow>=8.0.0
Requires-Dist: numpy>=1.21.0
Requires-Dist: requests>=2.25.0
Dynamic: author
Dynamic: author-email
Dynamic: classifier
Dynamic: description
Dynamic: description-content-type
Dynamic: home-page
Dynamic: requires-dist
Dynamic: requires-python
Dynamic: summary
